easyocr2/__init__.py
easyocr2/cli.py
easyocr2/config.py
easyocr2/craft.py
easyocr2/craft_utils.py
easyocr2/detection.py
easyocr2/detection_db.py
easyocr2/easyocr.py
easyocr2/export.py
easyocr2/imgproc.py
easyocr2/recognition.py
easyocr2/utils.py
easyocr2/model/__init__.py
easyocr2/model/model.py
easyocr2/model/modules.py
easyocr2/model/vgg_model.py
easyocr2-1.0.1.dist-info/licenses/LICENSE
easyocr2-1.0.1.dist-info/METADATA
easyocr2-1.0.1.dist-info/WHEEL
easyocr2-1.0.1.dist-info/entry_points.txt
easyocr2-1.0.1.dist-info/top_level.txt
easyocr2-1.0.1.dist-info/RECORD
