Metadata-Version: 2.4
Name: easyocr2
Version: 1.0.1
Summary: Next-generation OCR with 80+ languages - Ready-to-use OCR powered by deep learning
Home-page: https://github.com/cyberiums/EasyOCR
Download-URL: https://github.com/cyberiums/EasyOCR.git
Author: Cyberiums
Author-email: 
License: Apache License 2.0
Keywords: ocr,optical character recognition,deep learning,neural network,easyocr2
Classifier: Development Status :: 5 - Production/Stable
Classifier: Intended Audience :: Developers
Classifier: License :: OSI Approved :: Apache Software License
Classifier: Programming Language :: Python :: 3
Classifier: Programming Language :: Python :: 3.7
Classifier: Programming Language :: Python :: 3.8
Classifier: Programming Language :: Python :: 3.9
Classifier: Programming Language :: Python :: 3.10
Classifier: Programming Language :: Python :: 3.11
Requires-Python: >=3.7
License-File: LICENSE
Requires-Dist: torch
Requires-Dist: torchvision>=0.5
Requires-Dist: opencv-python-headless
Requires-Dist: scipy
Requires-Dist: numpy
Requires-Dist: Pillow
Requires-Dist: scikit-image
Requires-Dist: python-bidi
Requires-Dist: PyYAML
Requires-Dist: Shapely
Requires-Dist: pyclipper
Dynamic: author
Dynamic: classifier
Dynamic: description
Dynamic: description-content-type
Dynamic: download-url
Dynamic: home-page
Dynamic: keywords
Dynamic: license
Dynamic: license-file
Dynamic: requires-dist
Dynamic: requires-python
Dynamic: summary
